ap_python/__init__.py
ap_python/aspenhysys/__init__.py
ap_python/aspenhysys/application.py
ap_python/aspenplus/__init__.py
ap_python/aspenplus/application.py
ap_python-1.0.1.dist-info/METADATA
ap_python-1.0.1.dist-info/RECORD
ap_python-1.0.1.dist-info/WHEEL
ap_python-1.0.1.dist-info/top_level.txt
